GONGHAlphaAnomalyzer/__init__.py
GONGHAlphaAnomalyzer/anomalyzer.py
GONGHAlphaAnomalyzer/anova_analysis.py
GONGHAlphaAnomalyzer/best_ranges_calculator.py
GONGHAlphaAnomalyzer/cell_average_calculator.py
GONGHAlphaAnomalyzer/cell_range_calculator.py
GONGHAlphaAnomalyzer/demo.ipynb
GONGHAlphaAnomalyzer/performance_evaluator.py
GONGHAlphaAnomalyzer/plots_generator.py
GONGHAlphaAnomalyzer-0.1.0.dist-info/LICENSE
GONGHAlphaAnomalyzer-0.1.0.dist-info/METADATA
GONGHAlphaAnomalyzer-0.1.0.dist-info/WHEEL
GONGHAlphaAnomalyzer-0.1.0.dist-info/top_level.txt
GONGHAlphaAnomalyzer-0.1.0.dist-info/RECORD
