Metadata-Version: 2.1
Name: GONGHAlphaAnomalyzer
Version: 0.1.0
Summary: This software identifies anomalous observations captured by the GONG network.
Author: "Heba Mahdi"
Author-email: Heba Mahdi <hebamahdi@umsl.edu>
Project-URL: Homepage, https://bitbucket.org/dataresearchlab/gonghalphaanomalyzer/src/master/
Classifier: Programming Language :: Python :: 3
Classifier: License :: OSI Approved :: MIT License
Classifier: Operating System :: OS Independent
Requires-Python: >=3.10
License-File: LICENSE
Requires-Dist: matplotlib ==3.9.0
Requires-Dist: numpy ==2.0.0
Requires-Dist: opencv-python ==4.10.0.84
Requires-Dist: pandas ==2.2.2
Requires-Dist: pillow ==10.3.0
Requires-Dist: requests ==2.32.3
Requires-Dist: scikit-image ==0.24.0
Requires-Dist: scikit-learn ==1.5.0
Requires-Dist: scipy ==1.13.1
Requires-Dist: tqdm ==4.66.4
Requires-Dist: urllib3 ==2.2.2
Requires-Dist: notebook ==7.2.1
